netbox_api/__init__.py
netbox_api/cmdutil.py
netbox_api/config.py
netbox_api/jtom.py
netbox_api/main.py
netbox_api/sync.py
netbox_api/util.py
netbox_api/api/__init__.py
netbox_api/api/client.py
netbox_api/api/client_test.py
netbox_api/api/util.py
netbox_api/model/__init__.py
netbox_api/model/common.py
netbox_api/model/devices.py
netbox_api/model/interfaces.py
netbox_api/model/sites.py
netbox_api/model/tenancy.py
netbox_api-0.4.3.dist-info/DESCRIPTION.rst
netbox_api-0.4.3.dist-info/METADATA
netbox_api-0.4.3.dist-info/RECORD
netbox_api-0.4.3.dist-info/WHEEL
netbox_api-0.4.3.dist-info/entry_points.txt
netbox_api-0.4.3.dist-info/metadata.json
netbox_api-0.4.3.dist-info/top_level.txt
pynetbox/__init__.py
pynetbox/cmdutil.py
pynetbox/config.py
pynetbox/jtom.py
pynetbox/main.py
pynetbox/sync.py
pynetbox/util.py
pynetbox/api/__init__.py
pynetbox/api/client.py
pynetbox/api/client_test.py
pynetbox/api/util.py
pynetbox/dbapi/__init__.py
pynetbox/dbapi/client.py
pynetbox/model/__init__.py
pynetbox/model/common.py
pynetbox/model/dcim.py
pynetbox/model/dcim_interface.py
pynetbox/model/dcim_site.py
pynetbox/model/devices.py
pynetbox/model/interfaces.py
pynetbox/model/sites.py
pynetbox/model/tenancy.py
